pydatamail/__init__.py
pydatamail/_version.py
pydatamail/database.py
pydatamail/message.py
pydatamail/plots.py
pydatamail-0.0.10.dist-info/LICENSE
pydatamail-0.0.10.dist-info/METADATA
pydatamail-0.0.10.dist-info/WHEEL
pydatamail-0.0.10.dist-info/top_level.txt
pydatamail-0.0.10.dist-info/RECORD
