Metadata-Version: 2.1
Name: pydatamail
Version: 0.0.10
Summary: pydatamail - a python module to apply data science principles to email processing
Home-page: https://github.com/pyscioffice/pydatamail
Author: Jan Janssen
Author-email: jan.janssen@outlook.com
License: BSD
License-File: LICENSE
Requires-Dist: numpy (>=1.23.1)
Requires-Dist: tqdm (>=4.64.0)
Requires-Dist: pandas (>=1.4.3)
Requires-Dist: sqlalchemy (>=1.4.40)
Requires-Dist: matplotlib (>=3.5.2)
